[ {
  "id" : null,
  "vehicle" : {
    "id" : 1,
    "type" : "CAR",
    "vehicleNumber" : "ABC123",
    "routeFrom" : "Origin",
    "routeTo" : "Destination"
  },
  "description" : "Cargo 1",
  "weight" : 49.98,
  "status" : "OUT_FOR_DELIVERY"
}, {
  "id" : null,
  "vehicle" : {
    "id" : 2,
    "type" : "TRUCK",
    "vehicleNumber" : "DEF456",
    "routeFrom" : "Origin",
    "routeTo" : "Destination"
  },
  "description" : "Cargo 2",
  "weight" : 31.07,
  "status" : "LOST"
}, {
  "id" : null,
  "vehicle" : {
    "id" : 3,
    "type" : "TRAIN",
    "vehicleNumber" : "GHI789",
    "routeFrom" : "Origin",
    "routeTo" : "Destination"
  },
  "description" : "Cargo 3",
  "weight" : 66.62,
  "status" : "PENDING"
}, {
  "id" : null,
  "vehicle" : {
    "id" : 4,
    "type" : "PLANE",
    "vehicleNumber" : "JKL012",
    "routeFrom" : "Origin",
    "routeTo" : "Destination"
  },
  "description" : "Cargo 4",
  "weight" : 67.6,
  "status" : "RETURNED"
}, {
  "id" : null,
  "vehicle" : {
    "id" : 5,
    "type" : "SHIP",
    "vehicleNumber" : "MNO345",
    "routeFrom" : "Origin",
    "routeTo" : "Destination"
  },
  "description" : "Cargo 5",
  "weight" : 16.14,
  "status" : "IN_TRANSIT"
}, {
  "id" : null,
  "vehicle" : {
    "id" : 6,
    "type" : "HELICOPTER",
    "vehicleNumber" : "PQR678",
    "routeFrom" : "Origin",
    "routeTo" : "Destination"
  },
  "description" : "Cargo 6",
  "weight" : 48.45,
  "status" : "OUT_FOR_DELIVERY"
}, {
  "id" : null,
  "vehicle" : {
    "id" : 7,
    "type" : "DRONE",
    "vehicleNumber" : "STU901",
    "routeFrom" : "Origin",
    "routeTo" : "Destination"
  },
  "description" : "Cargo 7",
  "weight" : 51.74,
  "status" : "IN_TRANSIT"
}, {
  "id" : null,
  "vehicle" : {
    "id" : 8,
    "type" : "CAR",
    "vehicleNumber" : "VWX234",
    "routeFrom" : "Origin",
    "routeTo" : "Destination"
  },
  "description" : "Cargo 8",
  "weight" : 60.21,
  "status" : "RETURNED"
}, {
  "id" : null,
  "vehicle" : {
    "id" : 9,
    "type" : "TRUCK",
    "vehicleNumber" : "YZA567",
    "routeFrom" : "Origin",
    "routeTo" : "Destination"
  },
  "description" : "Cargo 9",
  "weight" : 55.53,
  "status" : "IN_TRANSIT"
}, {
  "id" : null,
  "vehicle" : {
    "id" : 10,
    "type" : "TRAIN",
    "vehicleNumber" : "BCD890",
    "routeFrom" : "Origin",
    "routeTo" : "Destination"
  },
  "description" : "Cargo 10",
  "weight" : 29.8,
  "status" : "PENDING"
}, {
  "id" : null,
  "vehicle" : {
    "id" : 1,
    "type" : "CAR",
    "vehicleNumber" : "ABC123",
    "routeFrom" : "Origin",
    "routeTo" : "Destination"
  },
  "description" : "Cargo 11",
  "weight" : 74.82,
  "status" : "IN_TRANSIT"
}, {
  "id" : null,
  "vehicle" : {
    "id" : 2,
    "type" : "TRUCK",
    "vehicleNumber" : "DEF456",
    "routeFrom" : "Origin",
    "routeTo" : "Destination"
  },
  "description" : "Cargo 12",
  "weight" : 42.25,
  "status" : "RETURNED"
}, {
  "id" : null,
  "vehicle" : {
    "id" : 3,
    "type" : "TRAIN",
    "vehicleNumber" : "GHI789",
    "routeFrom" : "Origin",
    "routeTo" : "Destination"
  },
  "description" : "Cargo 13",
  "weight" : 23.65,
  "status" : "OUT_FOR_DELIVERY"
}, {
  "id" : null,
  "vehicle" : {
    "id" : 4,
    "type" : "PLANE",
    "vehicleNumber" : "JKL012",
    "routeFrom" : "Origin",
    "routeTo" : "Destination"
  },
  "description" : "Cargo 14",
  "weight" : 27.14,
  "status" : "LOST"
}, {
  "id" : null,
  "vehicle" : {
    "id" : 5,
    "type" : "SHIP",
    "vehicleNumber" : "MNO345",
    "routeFrom" : "Origin",
    "routeTo" : "Destination"
  },
  "description" : "Cargo 15",
  "weight" : 55.89,
  "status" : "IN_TRANSIT"
}, {
  "id" : null,
  "vehicle" : {
    "id" : 6,
    "type" : "HELICOPTER",
    "vehicleNumber" : "PQR678",
    "routeFrom" : "Origin",
    "routeTo" : "Destination"
  },
  "description" : "Cargo 16",
  "weight" : 0.32,
  "status" : "RETURNED"
}, {
  "id" : null,
  "vehicle" : {
    "id" : 7,
    "type" : "DRONE",
    "vehicleNumber" : "STU901",
    "routeFrom" : "Origin",
    "routeTo" : "Destination"
  },
  "description" : "Cargo 17",
  "weight" : 45.91,
  "status" : "RETURNED"
}, {
  "id" : null,
  "vehicle" : {
    "id" : 8,
    "type" : "CAR",
    "vehicleNumber" : "VWX234",
    "routeFrom" : "Origin",
    "routeTo" : "Destination"
  },
  "description" : "Cargo 18",
  "weight" : 28.46,
  "status" : "IN_TRANSIT"
}, {
  "id" : null,
  "vehicle" : {
    "id" : 9,
    "type" : "TRUCK",
    "vehicleNumber" : "YZA567",
    "routeFrom" : "Origin",
    "routeTo" : "Destination"
  },
  "description" : "Cargo 19",
  "weight" : 70.69,
  "status" : "OUT_FOR_DELIVERY"
}, {
  "id" : null,
  "vehicle" : {
    "id" : 10,
    "type" : "TRAIN",
    "vehicleNumber" : "BCD890",
    "routeFrom" : "Origin",
    "routeTo" : "Destination"
  },
  "description" : "Cargo 20",
  "weight" : 43.59,
  "status" : "IN_TRANSIT"
}, {
  "id" : null,
  "vehicle" : {
    "id" : 1,
    "type" : "CAR",
    "vehicleNumber" : "ABC123",
    "routeFrom" : "Origin",
    "routeTo" : "Destination"
  },
  "description" : "Cargo 21",
  "weight" : 73.36,
  "status" : "DELIVERED"
}, {
  "id" : null,
  "vehicle" : {
    "id" : 2,
    "type" : "TRUCK",
    "vehicleNumber" : "DEF456",
    "routeFrom" : "Origin",
    "routeTo" : "Destination"
  },
  "description" : "Cargo 22",
  "weight" : 72.52,
  "status" : "DELIVERED"
}, {
  "id" : null,
  "vehicle" : {
    "id" : 3,
    "type" : "TRAIN",
    "vehicleNumber" : "GHI789",
    "routeFrom" : "Origin",
    "routeTo" : "Destination"
  },
  "description" : "Cargo 23",
  "weight" : 2.34,
  "status" : "IN_TRANSIT"
}, {
  "id" : null,
  "vehicle" : {
    "id" : 4,
    "type" : "PLANE",
    "vehicleNumber" : "JKL012",
    "routeFrom" : "Origin",
    "routeTo" : "Destination"
  },
  "description" : "Cargo 24",
  "weight" : 61.46,
  "status" : "IN_TRANSIT"
}, {
  "id" : null,
  "vehicle" : {
    "id" : 5,
    "type" : "SHIP",
    "vehicleNumber" : "MNO345",
    "routeFrom" : "Origin",
    "routeTo" : "Destination"
  },
  "description" : "Cargo 25",
  "weight" : 62.41,
  "status" : "LOST"
}, {
  "id" : null,
  "vehicle" : {
    "id" : 6,
    "type" : "HELICOPTER",
    "vehicleNumber" : "PQR678",
    "routeFrom" : "Origin",
    "routeTo" : "Destination"
  },
  "description" : "Cargo 26",
  "weight" : 70.45,
  "status" : "LOST"
}, {
  "id" : null,
  "vehicle" : {
    "id" : 7,
    "type" : "DRONE",
    "vehicleNumber" : "STU901",
    "routeFrom" : "Origin",
    "routeTo" : "Destination"
  },
  "description" : "Cargo 27",
  "weight" : 84.49,
  "status" : "RETURNED"
}, {
  "id" : null,
  "vehicle" : {
    "id" : 8,
    "type" : "CAR",
    "vehicleNumber" : "VWX234",
    "routeFrom" : "Origin",
    "routeTo" : "Destination"
  },
  "description" : "Cargo 28",
  "weight" : 83.57,
  "status" : "OUT_FOR_DELIVERY"
}, {
  "id" : null,
  "vehicle" : {
    "id" : 9,
    "type" : "TRUCK",
    "vehicleNumber" : "YZA567",
    "routeFrom" : "Origin",
    "routeTo" : "Destination"
  },
  "description" : "Cargo 29",
  "weight" : 19.68,
  "status" : "PENDING"
}, {
  "id" : null,
  "vehicle" : {
    "id" : 10,
    "type" : "TRAIN",
    "vehicleNumber" : "BCD890",
    "routeFrom" : "Origin",
    "routeTo" : "Destination"
  },
  "description" : "Cargo 30",
  "weight" : 31.68,
  "status" : "RETURNED"
}, {
  "id" : null,
  "vehicle" : {
    "id" : 1,
    "type" : "CAR",
    "vehicleNumber" : "ABC123",
    "routeFrom" : "Origin",
    "routeTo" : "Destination"
  },
  "description" : "Cargo 31",
  "weight" : 89.27,
  "status" : "DELIVERED"
}, {
  "id" : null,
  "vehicle" : {
    "id" : 2,
    "type" : "TRUCK",
    "vehicleNumber" : "DEF456",
    "routeFrom" : "Origin",
    "routeTo" : "Destination"
  },
  "description" : "Cargo 32",
  "weight" : 52.08,
  "status" : "OUT_FOR_DELIVERY"
}, {
  "id" : null,
  "vehicle" : {
    "id" : 3,
    "type" : "TRAIN",
    "vehicleNumber" : "GHI789",
    "routeFrom" : "Origin",
    "routeTo" : "Destination"
  },
  "description" : "Cargo 33",
  "weight" : 77.83,
  "status" : "LOST"
}, {
  "id" : null,
  "vehicle" : {
    "id" : 4,
    "type" : "PLANE",
    "vehicleNumber" : "JKL012",
    "routeFrom" : "Origin",
    "routeTo" : "Destination"
  },
  "description" : "Cargo 34",
  "weight" : 16.22,
  "status" : "DELIVERED"
}, {
  "id" : null,
  "vehicle" : {
    "id" : 5,
    "type" : "SHIP",
    "vehicleNumber" : "MNO345",
    "routeFrom" : "Origin",
    "routeTo" : "Destination"
  },
  "description" : "Cargo 35",
  "weight" : 38.8,
  "status" : "DELIVERED"
}, {
  "id" : null,
  "vehicle" : {
    "id" : 6,
    "type" : "HELICOPTER",
    "vehicleNumber" : "PQR678",
    "routeFrom" : "Origin",
    "routeTo" : "Destination"
  },
  "description" : "Cargo 36",
  "weight" : 40.88,
  "status" : "DELIVERED"
}, {
  "id" : null,
  "vehicle" : {
    "id" : 7,
    "type" : "DRONE",
    "vehicleNumber" : "STU901",
    "routeFrom" : "Origin",
    "routeTo" : "Destination"
  },
  "description" : "Cargo 37",
  "weight" : 93.53,
  "status" : "PENDING"
}, {
  "id" : null,
  "vehicle" : {
    "id" : 8,
    "type" : "CAR",
    "vehicleNumber" : "VWX234",
    "routeFrom" : "Origin",
    "routeTo" : "Destination"
  },
  "description" : "Cargo 38",
  "weight" : 60.8,
  "status" : "PENDING"
}, {
  "id" : null,
  "vehicle" : {
    "id" : 9,
    "type" : "TRUCK",
    "vehicleNumber" : "YZA567",
    "routeFrom" : "Origin",
    "routeTo" : "Destination"
  },
  "description" : "Cargo 39",
  "weight" : 43.57,
  "status" : "PENDING"
}, {
  "id" : null,
  "vehicle" : {
    "id" : 10,
    "type" : "TRAIN",
    "vehicleNumber" : "BCD890",
    "routeFrom" : "Origin",
    "routeTo" : "Destination"
  },
  "description" : "Cargo 40",
  "weight" : 81.64,
  "status" : "DELIVERED"
}, {
  "id" : null,
  "vehicle" : {
    "id" : 1,
    "type" : "CAR",
    "vehicleNumber" : "ABC123",
    "routeFrom" : "Origin",
    "routeTo" : "Destination"
  },
  "description" : "Cargo 41",
  "weight" : 83.44,
  "status" : "PENDING"
}, {
  "id" : null,
  "vehicle" : {
    "id" : 2,
    "type" : "TRUCK",
    "vehicleNumber" : "DEF456",
    "routeFrom" : "Origin",
    "routeTo" : "Destination"
  },
  "description" : "Cargo 42",
  "weight" : 50.89,
  "status" : "DELIVERED"
}, {
  "id" : null,
  "vehicle" : {
    "id" : 3,
    "type" : "TRAIN",
    "vehicleNumber" : "GHI789",
    "routeFrom" : "Origin",
    "routeTo" : "Destination"
  },
  "description" : "Cargo 43",
  "weight" : 96.38,
  "status" : "OUT_FOR_DELIVERY"
}, {
  "id" : null,
  "vehicle" : {
    "id" : 4,
    "type" : "PLANE",
    "vehicleNumber" : "JKL012",
    "routeFrom" : "Origin",
    "routeTo" : "Destination"
  },
  "description" : "Cargo 44",
  "weight" : 81.23,
  "status" : "IN_TRANSIT"
}, {
  "id" : null,
  "vehicle" : {
    "id" : 5,
    "type" : "SHIP",
    "vehicleNumber" : "MNO345",
    "routeFrom" : "Origin",
    "routeTo" : "Destination"
  },
  "description" : "Cargo 45",
  "weight" : 39.4,
  "status" : "LOST"
}, {
  "id" : null,
  "vehicle" : {
    "id" : 6,
    "type" : "HELICOPTER",
    "vehicleNumber" : "PQR678",
    "routeFrom" : "Origin",
    "routeTo" : "Destination"
  },
  "description" : "Cargo 46",
  "weight" : 36.11,
  "status" : "LOST"
}, {
  "id" : null,
  "vehicle" : {
    "id" : 7,
    "type" : "DRONE",
    "vehicleNumber" : "STU901",
    "routeFrom" : "Origin",
    "routeTo" : "Destination"
  },
  "description" : "Cargo 47",
  "weight" : 75.19,
  "status" : "PENDING"
}, {
  "id" : null,
  "vehicle" : {
    "id" : 8,
    "type" : "CAR",
    "vehicleNumber" : "VWX234",
    "routeFrom" : "Origin",
    "routeTo" : "Destination"
  },
  "description" : "Cargo 48",
  "weight" : 40.51,
  "status" : "DELIVERED"
}, {
  "id" : null,
  "vehicle" : {
    "id" : 9,
    "type" : "TRUCK",
    "vehicleNumber" : "YZA567",
    "routeFrom" : "Origin",
    "routeTo" : "Destination"
  },
  "description" : "Cargo 49",
  "weight" : 88.68,
  "status" : "DELIVERED"
}, {
  "id" : null,
  "vehicle" : {
    "id" : 10,
    "type" : "TRAIN",
    "vehicleNumber" : "BCD890",
    "routeFrom" : "Origin",
    "routeTo" : "Destination"
  },
  "description" : "Cargo 50",
  "weight" : 11.04,
  "status" : "DELIVERED"
}, {
  "id" : null,
  "vehicle" : {
    "id" : 1,
    "type" : "CAR",
    "vehicleNumber" : "ABC123",
    "routeFrom" : "Origin",
    "routeTo" : "Destination"
  },
  "description" : "Cargo 51",
  "weight" : 33.54,
  "status" : "PENDING"
}, {
  "id" : null,
  "vehicle" : {
    "id" : 2,
    "type" : "TRUCK",
    "vehicleNumber" : "DEF456",
    "routeFrom" : "Origin",
    "routeTo" : "Destination"
  },
  "description" : "Cargo 52",
  "weight" : 9.18,
  "status" : "DELIVERED"
}, {
  "id" : null,
  "vehicle" : {
    "id" : 3,
    "type" : "TRAIN",
    "vehicleNumber" : "GHI789",
    "routeFrom" : "Origin",
    "routeTo" : "Destination"
  },
  "description" : "Cargo 53",
  "weight" : 90.35,
  "status" : "LOST"
}, {
  "id" : null,
  "vehicle" : {
    "id" : 4,
    "type" : "PLANE",
    "vehicleNumber" : "JKL012",
    "routeFrom" : "Origin",
    "routeTo" : "Destination"
  },
  "description" : "Cargo 54",
  "weight" : 8.99,
  "status" : "DELIVERED"
}, {
  "id" : null,
  "vehicle" : {
    "id" : 5,
    "type" : "SHIP",
    "vehicleNumber" : "MNO345",
    "routeFrom" : "Origin",
    "routeTo" : "Destination"
  },
  "description" : "Cargo 55",
  "weight" : 81.93,
  "status" : "OUT_FOR_DELIVERY"
}, {
  "id" : null,
  "vehicle" : {
    "id" : 6,
    "type" : "HELICOPTER",
    "vehicleNumber" : "PQR678",
    "routeFrom" : "Origin",
    "routeTo" : "Destination"
  },
  "description" : "Cargo 56",
  "weight" : 36.35,
  "status" : "LOST"
}, {
  "id" : null,
  "vehicle" : {
    "id" : 7,
    "type" : "DRONE",
    "vehicleNumber" : "STU901",
    "routeFrom" : "Origin",
    "routeTo" : "Destination"
  },
  "description" : "Cargo 57",
  "weight" : 83.89,
  "status" : "LOST"
}, {
  "id" : null,
  "vehicle" : {
    "id" : 8,
    "type" : "CAR",
    "vehicleNumber" : "VWX234",
    "routeFrom" : "Origin",
    "routeTo" : "Destination"
  },
  "description" : "Cargo 58",
  "weight" : 80.65,
  "status" : "RETURNED"
}, {
  "id" : null,
  "vehicle" : {
    "id" : 9,
    "type" : "TRUCK",
    "vehicleNumber" : "YZA567",
    "routeFrom" : "Origin",
    "routeTo" : "Destination"
  },
  "description" : "Cargo 59",
  "weight" : 88.81,
  "status" : "DELIVERED"
}, {
  "id" : null,
  "vehicle" : {
    "id" : 10,
    "type" : "TRAIN",
    "vehicleNumber" : "BCD890",
    "routeFrom" : "Origin",
    "routeTo" : "Destination"
  },
  "description" : "Cargo 60",
  "weight" : 1.74,
  "status" : "DELIVERED"
}, {
  "id" : null,
  "vehicle" : {
    "id" : 1,
    "type" : "CAR",
    "vehicleNumber" : "ABC123",
    "routeFrom" : "Origin",
    "routeTo" : "Destination"
  },
  "description" : "Cargo 61",
  "weight" : 30.87,
  "status" : "LOST"
}, {
  "id" : null,
  "vehicle" : {
    "id" : 2,
    "type" : "TRUCK",
    "vehicleNumber" : "DEF456",
    "routeFrom" : "Origin",
    "routeTo" : "Destination"
  },
  "description" : "Cargo 62",
  "weight" : 55.23,
  "status" : "RETURNED"
}, {
  "id" : null,
  "vehicle" : {
    "id" : 3,
    "type" : "TRAIN",
    "vehicleNumber" : "GHI789",
    "routeFrom" : "Origin",
    "routeTo" : "Destination"
  },
  "description" : "Cargo 63",
  "weight" : 54.56,
  "status" : "OUT_FOR_DELIVERY"
}, {
  "id" : null,
  "vehicle" : {
    "id" : 4,
    "type" : "PLANE",
    "vehicleNumber" : "JKL012",
    "routeFrom" : "Origin",
    "routeTo" : "Destination"
  },
  "description" : "Cargo 64",
  "weight" : 37.23,
  "status" : "OUT_FOR_DELIVERY"
}, {
  "id" : null,
  "vehicle" : {
    "id" : 5,
    "type" : "SHIP",
    "vehicleNumber" : "MNO345",
    "routeFrom" : "Origin",
    "routeTo" : "Destination"
  },
  "description" : "Cargo 65",
  "weight" : 15.87,
  "status" : "LOST"
}, {
  "id" : null,
  "vehicle" : {
    "id" : 6,
    "type" : "HELICOPTER",
    "vehicleNumber" : "PQR678",
    "routeFrom" : "Origin",
    "routeTo" : "Destination"
  },
  "description" : "Cargo 66",
  "weight" : 6.13,
  "status" : "OUT_FOR_DELIVERY"
}, {
  "id" : null,
  "vehicle" : {
    "id" : 7,
    "type" : "DRONE",
    "vehicleNumber" : "STU901",
    "routeFrom" : "Origin",
    "routeTo" : "Destination"
  },
  "description" : "Cargo 67",
  "weight" : 37.07,
  "status" : "LOST"
}, {
  "id" : null,
  "vehicle" : {
    "id" : 8,
    "type" : "CAR",
    "vehicleNumber" : "VWX234",
    "routeFrom" : "Origin",
    "routeTo" : "Destination"
  },
  "description" : "Cargo 68",
  "weight" : 73.47,
  "status" : "DELIVERED"
}, {
  "id" : null,
  "vehicle" : {
    "id" : 9,
    "type" : "TRUCK",
    "vehicleNumber" : "YZA567",
    "routeFrom" : "Origin",
    "routeTo" : "Destination"
  },
  "description" : "Cargo 69",
  "weight" : 97.62,
  "status" : "RETURNED"
}, {
  "id" : null,
  "vehicle" : {
    "id" : 10,
    "type" : "TRAIN",
    "vehicleNumber" : "BCD890",
    "routeFrom" : "Origin",
    "routeTo" : "Destination"
  },
  "description" : "Cargo 70",
  "weight" : 68.42,
  "status" : "PENDING"
}, {
  "id" : null,
  "vehicle" : {
    "id" : 1,
    "type" : "CAR",
    "vehicleNumber" : "ABC123",
    "routeFrom" : "Origin",
    "routeTo" : "Destination"
  },
  "description" : "Cargo 71",
  "weight" : 32.4,
  "status" : "IN_TRANSIT"
}, {
  "id" : null,
  "vehicle" : {
    "id" : 2,
    "type" : "TRUCK",
    "vehicleNumber" : "DEF456",
    "routeFrom" : "Origin",
    "routeTo" : "Destination"
  },
  "description" : "Cargo 72",
  "weight" : 71.37,
  "status" : "OUT_FOR_DELIVERY"
}, {
  "id" : null,
  "vehicle" : {
    "id" : 3,
    "type" : "TRAIN",
    "vehicleNumber" : "GHI789",
    "routeFrom" : "Origin",
    "routeTo" : "Destination"
  },
  "description" : "Cargo 73",
  "weight" : 26.3,
  "status" : "PENDING"
}, {
  "id" : null,
  "vehicle" : {
    "id" : 4,
    "type" : "PLANE",
    "vehicleNumber" : "JKL012",
    "routeFrom" : "Origin",
    "routeTo" : "Destination"
  },
  "description" : "Cargo 74",
  "weight" : 80.58,
  "status" : "RETURNED"
}, {
  "id" : null,
  "vehicle" : {
    "id" : 5,
    "type" : "SHIP",
    "vehicleNumber" : "MNO345",
    "routeFrom" : "Origin",
    "routeTo" : "Destination"
  },
  "description" : "Cargo 75",
  "weight" : 39.03,
  "status" : "LOST"
}, {
  "id" : null,
  "vehicle" : {
    "id" : 6,
    "type" : "HELICOPTER",
    "vehicleNumber" : "PQR678",
    "routeFrom" : "Origin",
    "routeTo" : "Destination"
  },
  "description" : "Cargo 76",
  "weight" : 23.29,
  "status" : "PENDING"
}, {
  "id" : null,
  "vehicle" : {
    "id" : 7,
    "type" : "DRONE",
    "vehicleNumber" : "STU901",
    "routeFrom" : "Origin",
    "routeTo" : "Destination"
  },
  "description" : "Cargo 77",
  "weight" : 68.13,
  "status" : "IN_TRANSIT"
}, {
  "id" : null,
  "vehicle" : {
    "id" : 8,
    "type" : "CAR",
    "vehicleNumber" : "VWX234",
    "routeFrom" : "Origin",
    "routeTo" : "Destination"
  },
  "description" : "Cargo 78",
  "weight" : 47.46,
  "status" : "LOST"
}, {
  "id" : null,
  "vehicle" : {
    "id" : 9,
    "type" : "TRUCK",
    "vehicleNumber" : "YZA567",
    "routeFrom" : "Origin",
    "routeTo" : "Destination"
  },
  "description" : "Cargo 79",
  "weight" : 59.25,
  "status" : "RETURNED"
}, {
  "id" : null,
  "vehicle" : {
    "id" : 10,
    "type" : "TRAIN",
    "vehicleNumber" : "BCD890",
    "routeFrom" : "Origin",
    "routeTo" : "Destination"
  },
  "description" : "Cargo 80",
  "weight" : 33.52,
  "status" : "DELIVERED"
}, {
  "id" : null,
  "vehicle" : {
    "id" : 1,
    "type" : "CAR",
    "vehicleNumber" : "ABC123",
    "routeFrom" : "Origin",
    "routeTo" : "Destination"
  },
  "description" : "Cargo 81",
  "weight" : 3.13,
  "status" : "IN_TRANSIT"
}, {
  "id" : null,
  "vehicle" : {
    "id" : 2,
    "type" : "TRUCK",
    "vehicleNumber" : "DEF456",
    "routeFrom" : "Origin",
    "routeTo" : "Destination"
  },
  "description" : "Cargo 82",
  "weight" : 47.09,
  "status" : "RETURNED"
}, {
  "id" : null,
  "vehicle" : {
    "id" : 3,
    "type" : "TRAIN",
    "vehicleNumber" : "GHI789",
    "routeFrom" : "Origin",
    "routeTo" : "Destination"
  },
  "description" : "Cargo 83",
  "weight" : 16.11,
  "status" : "IN_TRANSIT"
}, {
  "id" : null,
  "vehicle" : {
    "id" : 4,
    "type" : "PLANE",
    "vehicleNumber" : "JKL012",
    "routeFrom" : "Origin",
    "routeTo" : "Destination"
  },
  "description" : "Cargo 84",
  "weight" : 12.99,
  "status" : "PENDING"
}, {
  "id" : null,
  "vehicle" : {
    "id" : 5,
    "type" : "SHIP",
    "vehicleNumber" : "MNO345",
    "routeFrom" : "Origin",
    "routeTo" : "Destination"
  },
  "description" : "Cargo 85",
  "weight" : 87.28,
  "status" : "PENDING"
}, {
  "id" : null,
  "vehicle" : {
    "id" : 6,
    "type" : "HELICOPTER",
    "vehicleNumber" : "PQR678",
    "routeFrom" : "Origin",
    "routeTo" : "Destination"
  },
  "description" : "Cargo 86",
  "weight" : 28.24,
  "status" : "IN_TRANSIT"
}, {
  "id" : null,
  "vehicle" : {
    "id" : 7,
    "type" : "DRONE",
    "vehicleNumber" : "STU901",
    "routeFrom" : "Origin",
    "routeTo" : "Destination"
  },
  "description" : "Cargo 87",
  "weight" : 89.67,
  "status" : "PENDING"
}, {
  "id" : null,
  "vehicle" : {
    "id" : 8,
    "type" : "CAR",
    "vehicleNumber" : "VWX234",
    "routeFrom" : "Origin",
    "routeTo" : "Destination"
  },
  "description" : "Cargo 88",
  "weight" : 47.93,
  "status" : "PENDING"
}, {
  "id" : null,
  "vehicle" : {
    "id" : 9,
    "type" : "TRUCK",
    "vehicleNumber" : "YZA567",
    "routeFrom" : "Origin",
    "routeTo" : "Destination"
  },
  "description" : "Cargo 89",
  "weight" : 94.8,
  "status" : "DELIVERED"
}, {
  "id" : null,
  "vehicle" : {
    "id" : 10,
    "type" : "TRAIN",
    "vehicleNumber" : "BCD890",
    "routeFrom" : "Origin",
    "routeTo" : "Destination"
  },
  "description" : "Cargo 90",
  "weight" : 71.27,
  "status" : "IN_TRANSIT"
}, {
  "id" : null,
  "vehicle" : {
    "id" : 1,
    "type" : "CAR",
    "vehicleNumber" : "ABC123",
    "routeFrom" : "Origin",
    "routeTo" : "Destination"
  },
  "description" : "Cargo 91",
  "weight" : 0.71,
  "status" : "IN_TRANSIT"
}, {
  "id" : null,
  "vehicle" : {
    "id" : 2,
    "type" : "TRUCK",
    "vehicleNumber" : "DEF456",
    "routeFrom" : "Origin",
    "routeTo" : "Destination"
  },
  "description" : "Cargo 92",
  "weight" : 27.21,
  "status" : "RETURNED"
}, {
  "id" : null,
  "vehicle" : {
    "id" : 3,
    "type" : "TRAIN",
    "vehicleNumber" : "GHI789",
    "routeFrom" : "Origin",
    "routeTo" : "Destination"
  },
  "description" : "Cargo 93",
  "weight" : 81.81,
  "status" : "IN_TRANSIT"
}, {
  "id" : null,
  "vehicle" : {
    "id" : 4,
    "type" : "PLANE",
    "vehicleNumber" : "JKL012",
    "routeFrom" : "Origin",
    "routeTo" : "Destination"
  },
  "description" : "Cargo 94",
  "weight" : 9.43,
  "status" : "RETURNED"
}, {
  "id" : null,
  "vehicle" : {
    "id" : 5,
    "type" : "SHIP",
    "vehicleNumber" : "MNO345",
    "routeFrom" : "Origin",
    "routeTo" : "Destination"
  },
  "description" : "Cargo 95",
  "weight" : 95.77,
  "status" : "DELIVERED"
}, {
  "id" : null,
  "vehicle" : {
    "id" : 6,
    "type" : "HELICOPTER",
    "vehicleNumber" : "PQR678",
    "routeFrom" : "Origin",
    "routeTo" : "Destination"
  },
  "description" : "Cargo 96",
  "weight" : 38.09,
  "status" : "OUT_FOR_DELIVERY"
}, {
  "id" : null,
  "vehicle" : {
    "id" : 7,
    "type" : "DRONE",
    "vehicleNumber" : "STU901",
    "routeFrom" : "Origin",
    "routeTo" : "Destination"
  },
  "description" : "Cargo 97",
  "weight" : 37.33,
  "status" : "DELIVERED"
}, {
  "id" : null,
  "vehicle" : {
    "id" : 8,
    "type" : "CAR",
    "vehicleNumber" : "VWX234",
    "routeFrom" : "Origin",
    "routeTo" : "Destination"
  },
  "description" : "Cargo 98",
  "weight" : 32.83,
  "status" : "IN_TRANSIT"
}, {
  "id" : null,
  "vehicle" : {
    "id" : 9,
    "type" : "TRUCK",
    "vehicleNumber" : "YZA567",
    "routeFrom" : "Origin",
    "routeTo" : "Destination"
  },
  "description" : "Cargo 99",
  "weight" : 11.85,
  "status" : "PENDING"
}, {
  "id" : null,
  "vehicle" : {
    "id" : 10,
    "type" : "TRAIN",
    "vehicleNumber" : "BCD890",
    "routeFrom" : "Origin",
    "routeTo" : "Destination"
  },
  "description" : "Cargo 100",
  "weight" : 65.27,
  "status" : "PENDING"
} ]